LICENSE
MANIFEST.in
README.md
setup.py
netbox3_bgp_kani_fork.egg-info/PKG-INFO
netbox3_bgp_kani_fork.egg-info/SOURCES.txt
netbox3_bgp_kani_fork.egg-info/dependency_links.txt
netbox3_bgp_kani_fork.egg-info/top_level.txt
netbox_bgp/__init__.py
netbox_bgp/admin.py
netbox_bgp/choices.py
netbox_bgp/filters.py
netbox_bgp/forms.py
netbox_bgp/graphql.py
netbox_bgp/models.py
netbox_bgp/navigation.py
netbox_bgp/tables.py
netbox_bgp/template_content.py
netbox_bgp/urls.py
netbox_bgp/version.py
netbox_bgp/views.py
netbox_bgp/api/__init__.py
netbox_bgp/api/serializers.py
netbox_bgp/api/urls.py
netbox_bgp/api/views.py
netbox_bgp/migrations/0001_initial.py
netbox_bgp/migrations/0002_netbox_bgp.py
netbox_bgp/migrations/0003_netbox_bgp.py
netbox_bgp/migrations/0004_netbox_bgp.py
netbox_bgp/migrations/0005_netbox_bgp.py
netbox_bgp/migrations/0006_netbox_bgp.py
netbox_bgp/migrations/0007_netbox_bgp.py
netbox_bgp/migrations/0008_netbox_bgp.py
netbox_bgp/migrations/0009_netbox_bgp.py
netbox_bgp/migrations/0010_netbox_bgp.py
netbox_bgp/migrations/0011_netbox_bgp.py
netbox_bgp/migrations/0012_netbox_bgp.py
netbox_bgp/migrations/0013_netbox_bgp.py
netbox_bgp/migrations/0014_netbox_bgp.py
netbox_bgp/migrations/0015_netbox_bgp.py
netbox_bgp/migrations/0016_netbox_bgp.py
netbox_bgp/migrations/0017_netbox_bgp.py
netbox_bgp/migrations/0018_netbox_bgp.py
netbox_bgp/migrations/0019_netbox_bgp.py
netbox_bgp/migrations/0020_netbox_bgp.py
netbox_bgp/migrations/0021_netbox32_support.py
netbox_bgp/migrations/0022_netbox_bgp.py
netbox_bgp/migrations/0023_netbox_bgp.py
netbox_bgp/migrations/0024_netbox_bgp.py
netbox_bgp/migrations/0025_netbox_bgp.py
netbox_bgp/migrations/__init__.py
netbox_bgp/templates/netbox_bgp/asn.html
netbox_bgp/templates/netbox_bgp/asn_list.html
netbox_bgp/templates/netbox_bgp/asn_migrate.html
netbox_bgp/templates/netbox_bgp/bgppeergroup.html
netbox_bgp/templates/netbox_bgp/bgpsession.html
netbox_bgp/templates/netbox_bgp/bgpsession_list.html
netbox_bgp/templates/netbox_bgp/community.html
netbox_bgp/templates/netbox_bgp/device_extend.html
netbox_bgp/templates/netbox_bgp/prefixlist.html
netbox_bgp/templates/netbox_bgp/prefixlistrule.html
