Metadata-Version: 2.1
Name: netbox3-bgp-kani-fork
Version: 0.7.0
Summary: BGP related stuff
Home-page: https://github.com/k01ek/netbox-bgp
Author: Nikolay Yuzefovich
Author-email: mgk.kolek@gmail.com
License: UNKNOWN
Platform: UNKNOWN
Classifier: Development Status :: 2 - Pre-Alpha
Classifier: License :: OSI Approved :: Apache Software License
Classifier: Framework :: Django
Classifier: Programming Language :: Python :: 3
License-File: LICENSE
